iojobs/__init__.py
iojobs/_internal/__init__.py
iojobs/_internal/_types.py
iojobs/_internal/cron_parser.py
iojobs/_internal/durable/__init__.py
iojobs/_internal/durable/abc.py
iojobs/_internal/durable/sqlite.py
iojobs/_internal/enums.py
iojobs/_internal/exceptions.py
iojobs/_internal/executors.py
iojobs/_internal/func_wrapper.py
iojobs/_internal/job_executor.py
iojobs/_internal/scheduler.py
iojobs/errors/__init__.py
iojobs/py.typed
iojobs-0.1.0.dist-info/WHEEL
iojobs-0.1.0.dist-info/METADATA
iojobs-0.1.0.dist-info/RECORD
